hygge/__init__.py
hygge/get.py
hygge-0.1.3.dist-info/WHEEL
hygge-0.1.3.dist-info/METADATA
hygge-0.1.3.dist-info/RECORD
