Metadata-Version: 2.1
Name: hygge
Version: 0.1.3
Summary: A cozzy('hygge') way to get json response back asynchronously
Home-page: https://github.com/Proteusiq/hygge
License: UNKNOWN
Keywords: http,requests,json,api
Author: Prayson Wilfred Daniel
Author-email: praysonwilfred@gmail.com
Requires-Python: >=3.6,<4.0
Classifier: Programming Language :: Python :: 3
Classifier: Programming Language :: Python :: 3.6
Classifier: Programming Language :: Python :: 3.7
Requires-Dist: aiohttp (>=3.5,<4.0)
Project-URL: Repository, https://github.com/Proteusiq/hygge
